check_sdist/__init__.py
check_sdist/__main__.py
check_sdist/backends.py
check_sdist/git.py
check_sdist/inject.py
check_sdist/py.typed
check_sdist/schema.py
check_sdist/sdist.py
check_sdist/_compat/__init__.py
check_sdist/_compat/tomllib.py
check_sdist/resources/__init__.py
check_sdist/resources/check-sdist.schema.json
check_sdist/resources/default-ignore.txt
check_sdist/resources/junk-paths.txt
check_sdist-1.3.2.dist-info/METADATA
check_sdist-1.3.2.dist-info/WHEEL
check_sdist-1.3.2.dist-info/entry_points.txt
check_sdist-1.3.2.dist-info/licenses/LICENSE
check_sdist-1.3.2.dist-info/RECORD
