Metadata-Version: 2.4
Name: check-sdist
Version: 1.3.2
Summary: Check the contents of an SDist vs. git
Project-URL: Homepage, https://github.com/henryiii/check-sdist
Project-URL: Bug Tracker, https://github.com/henryiii/check-sdist/issues
Project-URL: Changelog, https://github.com/henryiii/check-sdist/releases
Author-email: Henry Schreiner <henryschreineriii@gmail.com>
License-Expression: BSD-3-Clause
License-File: LICENSE
Keywords: lint,packaging,sdist
Classifier: Development Status :: 5 - Production/Stable
Classifier: Intended Audience :: Developers
Classifier: Operating System :: OS Independent
Classifier: Programming Language :: Python
Classifier: Programming Language :: Python :: 3
Classifier: Programming Language :: Python :: 3 :: Only
Classifier: Programming Language :: Python :: 3.9
Classifier: Programming Language :: Python :: 3.10
Classifier: Programming Language :: Python :: 3.11
Classifier: Programming Language :: Python :: 3.12
Classifier: Programming Language :: Python :: 3.13
Classifier: Programming Language :: Python :: 3.14
Classifier: Typing :: Typed
Requires-Python: >=3.9
Requires-Dist: build>=1.2
Requires-Dist: pathspec
Requires-Dist: tomli; python_version < '3.11'
Provides-Extra: uv
Requires-Dist: uv; extra == 'uv'
